<?xml version="1.0" encoding="UTF-8"?>
<launch4jConfig>
  <dontWrapJar>false</dontWrapJar>
  <headerType>gui</headerType>
  <jar>build\libs\ExampleLauncher-1.0-SNAPSHOT.jar</jar>
  <outfile>C:\Users\DELL\Desktop\ExampleLauncher.exe</outfile>
  <errTitle>ExampleLauncher Error</errTitle>
  <cmdLine></cmdLine>
  <chdir></chdir>
  <priority>normal</priority>
  <downloadUrl>https://adoptium.net/temurin/releases/?version=21</downloadUrl>
  <supportUrl></supportUrl>
  <stayAlive>false</stayAlive>
  <restartOnCrash>false</restartOnCrash>
  <manifest></manifest>
  <icon>C:\Users\DELL\Downloads\559778729_17864369643471178_6326753109871118797_n.ico</icon>
  <jre>
    <path>%JAVA_HOME%;%PATH%</path>
    <requiresJdk>false</requiresJdk>
    <requires64Bit>false</requires64Bit>
    <minVersion>21</minVersion>
    <maxVersion></maxVersion>
    <opt>-Xmx8G</opt>
  </jre>
  <versionInfo>
    <fileVersion>1.0.0.0</fileVersion>
    <txtFileVersion>1.0.0</txtFileVersion>
    <fileDescription>ExampleLauncher - Minecraft Launcher for Melonya Server</fileDescription>
    <copyright>Copyright © 2024</copyright>
    <productVersion>1.0.0.0</productVersion>
    <txtProductVersion>1.0.0</txtProductVersion>
    <productName>ExampleLauncher</productName>
    <companyName>ExampleLauncher</companyName>
    <internalName>ExampleLauncher</internalName>
    <originalFilename>ExampleLauncher.exe</originalFilename>
    <trademarks></trademarks>
    <language>TURKISH</language>
  </versionInfo>
</launch4jConfig>